{"chunk_definitions":[{"row":11,"row_count":1,"visible":true,"expansion_state":0,"options":{"engine":"r","label":"unnamed-chunk-50"},"document_id":"CC6BCE31","chunk_id":"cwi5rb5ob6u40","chunk_label":"unnamed-chunk-1"},{"row":32,"row_count":1,"visible":true,"expansion_state":0,"options":{"engine":"r","label":"unnamed-chunk-2"},"document_id":"CC6BCE31","chunk_id":"cih2a9wr2uit2","chunk_label":"unnamed-chunk-2"},{"row":46,"row_count":1,"visible":true,"expansion_state":0,"options":{"engine":"r","label":"unnamed-chunk-52"},"document_id":"CC6BCE31","chunk_id":"cypv2jqnk7w3t","chunk_label":"unnamed-chunk-3"},{"row":58,"row_count":1,"visible":true,"expansion_state":0,"options":{"engine":"r","label":"unnamed-chunk-53"},"document_id":"CC6BCE31","chunk_id":"c7cracebze8wp","chunk_label":"unnamed-chunk-4"},{"row":63,"row_count":1,"visible":true,"expansion_state":0,"options":{"engine":"r","label":"unnamed-chunk-54"},"document_id":"CC6BCE31","chunk_id":"cwyjkt4sxk2f5","chunk_label":"unnamed-chunk-5"},{"row":68,"row_count":1,"visible":true,"expansion_state":0,"options":{"engine":"r","label":"unnamed-chunk-55"},"document_id":"CC6BCE31","chunk_id":"co2q6xv7c8x2o","chunk_label":"unnamed-chunk-6"},{"row":75,"row_count":1,"visible":true,"expansion_state":0,"options":{"engine":"r","label":"unnamed-chunk-56"},"document_id":"CC6BCE31","chunk_id":"csd594i47j2sb","chunk_label":"unnamed-chunk-7"},{"row":79,"row_count":1,"visible":true,"expansion_state":0,"options":{"engine":"r","label":"unnamed-chunk-57"},"document_id":"CC6BCE31","chunk_id":"cswn5jdjld6o5","chunk_label":"unnamed-chunk-8"},{"row":106,"row_count":1,"visible":true,"expansion_state":0,"options":{"engine":"r","label":"unnamed-chunk-58"},"document_id":"CC6BCE31","chunk_id":"c6u1b75z3f43z","chunk_label":"unnamed-chunk-9"},{"row":118,"row_count":1,"visible":true,"expansion_state":0,"options":{"engine":"r","label":"unnamed-chunk-59"},"document_id":"CC6BCE31","chunk_id":"c4hv9aev4s5jv","chunk_label":"unnamed-chunk-10"},{"row":133,"row_count":1,"visible":true,"expansion_state":0,"options":{"engine":"r","label":"unnamed-chunk-60"},"document_id":"CC6BCE31","chunk_id":"ct3n083q7dqk0","chunk_label":"unnamed-chunk-11"},{"row":144,"row_count":1,"visible":true,"expansion_state":0,"options":{"engine":"r","label":"unnamed-chunk-61"},"document_id":"CC6BCE31","chunk_id":"cswc9kdigmhfy","chunk_label":"unnamed-chunk-12"},{"row":183,"row_count":1,"visible":true,"expansion_state":0,"options":{"engine":"r","label":"unnamed-chunk-62"},"document_id":"CC6BCE31","chunk_id":"c7alsxernfac4","chunk_label":"unnamed-chunk-13"},{"row":191,"row_count":1,"visible":true,"expansion_state":0,"options":{"engine":"r","label":"unnamed-chunk-63"},"document_id":"CC6BCE31","chunk_id":"cy6fcfyeuqn7c","chunk_label":"unnamed-chunk-14"},{"row":195,"row_count":1,"visible":true,"expansion_state":0,"options":{"engine":"r","label":"unnamed-chunk-64"},"document_id":"CC6BCE31","chunk_id":"cuqjcu5l6fz9f","chunk_label":"unnamed-chunk-15"},{"row":205,"row_count":1,"visible":true,"expansion_state":0,"options":{"engine":"r","label":"unnamed-chunk-65"},"document_id":"CC6BCE31","chunk_id":"csy02u4nlp722","chunk_label":"unnamed-chunk-16"},{"row":216,"row_count":1,"visible":true,"expansion_state":0,"options":{"engine":"r","label":"unnamed-chunk-66"},"document_id":"CC6BCE31","chunk_id":"cosjcgj5juyns","chunk_label":"unnamed-chunk-17"},{"row":278,"row_count":1,"visible":true,"expansion_state":0,"options":{"engine":"r","label":"unnamed-chunk-67"},"document_id":"CC6BCE31","chunk_id":"cv7rk405vv3ho","chunk_label":"unnamed-chunk-18"},{"row":306,"row_count":1,"visible":true,"expansion_state":0,"options":{"engine":"r","label":"unnamed-chunk-68"},"document_id":"CC6BCE31","chunk_id":"c7xzqrx650v6c","chunk_label":"unnamed-chunk-19"},{"row":319,"row_count":1,"visible":true,"expansion_state":0,"options":{"engine":"r","label":"unnamed-chunk-69"},"document_id":"CC6BCE31","chunk_id":"czp9dyaa98dvj","chunk_label":"unnamed-chunk-20"},{"row":324,"row_count":1,"visible":true,"expansion_state":0,"options":{"engine":"r","label":"unnamed-chunk-70"},"document_id":"CC6BCE31","chunk_id":"c2nknlmyoh2fn","chunk_label":"unnamed-chunk-21"},{"row":331,"row_count":1,"visible":true,"expansion_state":0,"options":{"engine":"r","label":"unnamed-chunk-71"},"document_id":"CC6BCE31","chunk_id":"chgv3iz8gnv4h","chunk_label":"unnamed-chunk-22"},{"row":337,"row_count":1,"visible":true,"expansion_state":0,"options":{"engine":"r","label":"unnamed-chunk-72"},"document_id":"CC6BCE31","chunk_id":"cdhatkzt8hn79","chunk_label":"unnamed-chunk-23"},{"row":341,"row_count":1,"visible":true,"expansion_state":0,"options":{"engine":"r","label":"unnamed-chunk-73"},"document_id":"CC6BCE31","chunk_id":"c3hpl3eycv9sg","chunk_label":"unnamed-chunk-24"},{"row":345,"row_count":1,"visible":true,"expansion_state":0,"options":{"engine":"r","label":"unnamed-chunk-74"},"document_id":"CC6BCE31","chunk_id":"cmnm9clrgs0o6","chunk_label":"unnamed-chunk-25"},{"row":354,"row_count":1,"visible":true,"expansion_state":0,"options":{"engine":"r","label":"unnamed-chunk-75"},"document_id":"CC6BCE31","chunk_id":"ctrkvyemxttiz","chunk_label":"unnamed-chunk-26"},{"row":363,"row_count":1,"visible":true,"expansion_state":0,"options":{"engine":"r","label":"unnamed-chunk-76"},"document_id":"CC6BCE31","chunk_id":"csj7okjr1hcr5","chunk_label":"unnamed-chunk-27"},{"row":370,"row_count":1,"visible":true,"expansion_state":0,"options":{"engine":"r","label":"unnamed-chunk-77"},"document_id":"CC6BCE31","chunk_id":"cjct18fhvcoue","chunk_label":"unnamed-chunk-28"},{"row":379,"row_count":1,"visible":true,"expansion_state":0,"options":{"engine":"r","label":"unnamed-chunk-78"},"document_id":"CC6BCE31","chunk_id":"c61wwjndmf9nh","chunk_label":"unnamed-chunk-29"},{"row":382,"row_count":1,"visible":true,"expansion_state":0,"options":{"engine":"r","label":"unnamed-chunk-79"},"document_id":"CC6BCE31","chunk_id":"cgvce6q41ijhk","chunk_label":"unnamed-chunk-30"},{"row":388,"row_count":1,"visible":true,"expansion_state":0,"options":{"engine":"r","label":"unnamed-chunk-80"},"document_id":"CC6BCE31","chunk_id":"cdx84aik6vd7j","chunk_label":"unnamed-chunk-31"},{"row":397,"row_count":1,"visible":true,"expansion_state":0,"options":{"engine":"r","label":"unnamed-chunk-81"},"document_id":"CC6BCE31","chunk_id":"c25agiiaxudif","chunk_label":"unnamed-chunk-32"},{"row":411,"row_count":1,"visible":true,"expansion_state":0,"options":{"engine":"r","label":"unnamed-chunk-82"},"document_id":"CC6BCE31","chunk_id":"coted4eizzup1","chunk_label":"unnamed-chunk-33"},{"row":415,"row_count":1,"visible":true,"expansion_state":0,"options":{"engine":"r","label":"unnamed-chunk-83"},"document_id":"CC6BCE31","chunk_id":"czly4cbw0fpid","chunk_label":"unnamed-chunk-34"},{"row":426,"row_count":1,"visible":true,"expansion_state":0,"options":{"engine":"r","label":"unnamed-chunk-84"},"document_id":"CC6BCE31","chunk_id":"c3fs0tzbmpgg7","chunk_label":"unnamed-chunk-35"},{"row":432,"row_count":1,"visible":true,"expansion_state":0,"options":{"engine":"r","label":"unnamed-chunk-85"},"document_id":"CC6BCE31","chunk_id":"c0zkcn1wxd89x","chunk_label":"unnamed-chunk-36"},{"row":443,"row_count":1,"visible":true,"expansion_state":0,"options":{"engine":"r","label":"unnamed-chunk-86"},"document_id":"CC6BCE31","chunk_id":"ca9chdjjyumya","chunk_label":"unnamed-chunk-37"},{"row":449,"row_count":1,"visible":true,"expansion_state":0,"options":{"engine":"r","label":"unnamed-chunk-87"},"document_id":"CC6BCE31","chunk_id":"ck6629t00pcl6","chunk_label":"unnamed-chunk-38"},{"row":461,"row_count":1,"visible":true,"expansion_state":0,"options":{"engine":"r","label":"unnamed-chunk-88"},"document_id":"CC6BCE31","chunk_id":"c4bnrafjxrwl5","chunk_label":"unnamed-chunk-39"}],"doc_write_time":1670999285,"chunk_rendered_width":700}